<?xml version="1.0" encoding="UTF-8"?>
<objects serializationModel="Studio.02.02.00">
	<object class="AudioFile" id="{b38092c4-3416-46ad-a3be-56be15343326}">
		<property name="assetPath">
			<value>COMRadio_Shortwave Radio Calls 02_PSE_OS_KZXhv (Freeze) [2024-05-15 143935].wav</value>
		</property>
		<property name="frequencyInKHz">
			<value>192</value>
		</property>
		<property name="channelCount">
			<value>2</value>
		</property>
		<property name="length">
			<value>1.3500052083333334</value>
		</property>
		<relationship name="masterAssetFolder">
			<destination>{d28b04c0-540f-4140-b164-16a8a6d7f235}</destination>
		</relationship>
	</object>
</objects>
