<?xml version="1.0" encoding="UTF-8"?>
<objects serializationModel="Studio.02.02.00">
	<object class="AudioFile" id="{cfbcb7a1-2576-47bc-a69b-67ac6714d40a}">
		<property name="assetPath">
			<value>player take damage crashes [2024-05-02 140806].wav</value>
		</property>
		<property name="frequencyInKHz">
			<value>44.0999985</value>
		</property>
		<property name="channelCount">
			<value>1</value>
		</property>
		<property name="length">
			<value>0.45102040816326533</value>
		</property>
		<relationship name="masterAssetFolder">
			<destination>{d28b04c0-540f-4140-b164-16a8a6d7f235}</destination>
		</relationship>
	</object>
</objects>
